<?xml version="1.0"?>

<model-hints>
	<model name="com.cignexdatamatics.wrm.model.BookingAttendees">
		<field name="attendeesId" type="long" />
		<field name="bookingId" type="long" />
	</model>
	<model name="com.cignexdatamatics.wrm.model.BookingFacilityMapping">
		<field name="bookingId" type="long" />
		<field name="facilitiesId" type="long" />
	</model>
	<model name="com.cignexdatamatics.wrm.model.BookingRooms">
		<field name="BRMappingId" type="long" />
		<field name="bookingId" type="long" />
		<field name="roomId" type="long" />
		<field name="bookingDate" type="Date" />
	</model>
	<model name="com.cignexdatamatics.wrm.model.CityMaster">
		<field name="cityId" type="long" />
		<field name="cityName" type="String" />
	</model>
	<model name="com.cignexdatamatics.wrm.model.FacilityMaster">
		<field name="facilitiesId" type="long" />
		<field name="facilitiesName" type="String" />
		<field name="facilitiesDesc" type="String" />
	</model>
	<model name="com.cignexdatamatics.wrm.model.FloorMaster">
		<field name="floorId" type="long" />
		<field name="locationId" type="long" />
		<field name="floorName" type="String" />
	</model>
	<model name="com.cignexdatamatics.wrm.model.LocationMaster">
		<field name="locationId" type="long" />
		<field name="cityId" type="long" />
		<field name="locationName" type="String" />
	</model>
	<model name="com.cignexdatamatics.wrm.model.NewBooking">
		<field name="bookingId" type="long" />
		<field name="meetingTitle" type="String" />
		<field name="meetingDesc" type="String" />
		<field name="hostId" type="long" />
		<field name="fromDate" type="Date" />
		<field name="toDate" type="Date" />
		<field name="startTime" type="String" />
		<field name="endTime" type="String" />
	</model>
	<model name="com.cignexdatamatics.wrm.model.RoomFacilityMapping">
		<field name="roomId" type="long" />
		<field name="facilitiesId" type="long" />
	</model>
	<model name="com.cignexdatamatics.wrm.model.RoomMaster">
		<field name="roomId" type="long" />
		<field name="cityId" type="long" />
		<field name="locationId" type="long" />
		<field name="floorId" type="long" />
		<field name="roomName" type="String" />
		<field name="capacity" type="long" />
		<field name="extension" type="long" />
	</model>
</model-hints>